setup.py
django_inlines/__init__.py
django_inlines/inlines.py
django_inlines/samples.py
django_inlines.egg-info/PKG-INFO
django_inlines.egg-info/SOURCES.txt
django_inlines.egg-info/dependency_links.txt
django_inlines.egg-info/requires.txt
django_inlines.egg-info/top_level.txt
