Metadata-Version: 1.0
Name: django-inlines
Version: 0.7
Summary: For embedding anything you'd like into text in your django apps.
Home-page: http://github.com/mintchaos/django_inlines
Author: Christian Metts
Author-email: xian@mintchaos.com
License: BSD
Platform: UNKNOWN
Classifier: Development Status :: 4 - Beta
Classifier: Framework :: Django
Classifier: Intended Audience :: Developers
Classifier: License :: OSI Approved :: BSD License
Classifier: Operating System :: OS Independent
Classifier: Programming Language :: Python
Classifier: Topic :: Internet :: WWW/HTTP
